README.md
setup.py
cpp_extensions/custom_operator_extension.cpp
torch_cfu.egg-info/PKG-INFO
torch_cfu.egg-info/SOURCES.txt
torch_cfu.egg-info/dependency_links.txt
torch_cfu.egg-info/top_level.txt
utils/__init__.py
utils/custom_device_mode.py